langchain_together/__init__.py
langchain_together/chat_models.py
langchain_together/embeddings.py
langchain_together/llms.py
langchain_together/py.typed
langchain_together-0.3.1.dist-info/LICENSE
langchain_together-0.3.1.dist-info/METADATA
langchain_together-0.3.1.dist-info/WHEEL
langchain_together-0.3.1.dist-info/RECORD
