Metadata-Version: 2.3
Name: langchain-together
Version: 0.3.1
Summary: An integration package connecting Together AI and LangChain
License: MIT
Requires-Python: >=3.9,<4.0
Classifier: License :: OSI Approved :: MIT License
Classifier: Programming Language :: Python :: 3
Classifier: Programming Language :: Python :: 3.9
Classifier: Programming Language :: Python :: 3.10
Classifier: Programming Language :: Python :: 3.11
Classifier: Programming Language :: Python :: 3.12
Classifier: Programming Language :: Python :: 3.13
Requires-Dist: aiohttp (>=3.9.1,<4.0.0)
Requires-Dist: langchain-core (>=0.3.29,<0.4.0)
Requires-Dist: langchain-openai (>=0.3,<0.4)
Requires-Dist: requests (>=2,<3)
Project-URL: Repository, https://github.com/langchain-ai/langchain-together
Project-URL: Release Notes, https://github.com/langchain-ai/langchain-together/releases
Project-URL: Source Code, https://github.com/langchain-ai/langchain-together/tree/main/libs/together
